cursofiap/__init__.py
cursofiap/core.py
rvgarci_cursofiap_package-1.0.0.dist-info/METADATA
rvgarci_cursofiap_package-1.0.0.dist-info/WHEEL
rvgarci_cursofiap_package-1.0.0.dist-info/top_level.txt
rvgarci_cursofiap_package-1.0.0.dist-info/RECORD
