Metadata-Version: 2.4
Name: rvgarci-cursofiap-package
Version: 1.0.0
Summary: Descricao da sua lib cursofiap
Home-page: https://github.com/rvgarci/cursofiap.git
Author: Rafael Garcia
Author-email: rvgarci@gmail.com
License: MIT
Dynamic: author
Dynamic: author-email
Dynamic: description
Dynamic: description-content-type
Dynamic: home-page
Dynamic: license
Dynamic: summary
